examples/__init__.py
examples/delete_pro_forma_invoice.py
examples/generate_invoice.py
examples/query_invoice_pdf.py
examples/query_invoice_xml.py
examples/query_tax_payer.py
examples/register_credit_entry.py
examples/storno.py
szamlazz/__init__.py
szamlazz/client.py
szamlazz/models.py
szamlazz/templates.py
szamlazz/version.py
szamlazz/xsd.py
szamlazz_py-1.5.1.dist-info/licenses/LICENSE
szamlazz_py-1.5.1.dist-info/METADATA
szamlazz_py-1.5.1.dist-info/WHEEL
szamlazz_py-1.5.1.dist-info/top_level.txt
szamlazz_py-1.5.1.dist-info/RECORD
