Metadata-Version: 2.4
Name: szamlazz.py
Version: 1.5.1
Summary: Python client for Szamlazz.hu :: Számla Agent
Home-page: https://github.com/theriverman/szamlazz.py
Author: Kristof Daja (theriverman)
Author-email: cowling_benzene0r@icloud.com
License: MIT License | Copyright (c) 2020 — 2025 Kristof Daja
Project-URL: Bug Tracker, https://github.com/theriverman/szamlazz.py/issues
Classifier: Environment :: Web Environment
Classifier: Intended Audience :: Developers
Classifier: License :: OSI Approved :: MIT License
Classifier: Operating System :: OS Independent
Classifier: Programming Language :: Python
Classifier: Programming Language :: Python :: 3.11
Classifier: Programming Language :: Python :: 3.12
Classifier: Programming Language :: Python :: 3.13
Requires-Python: >=3.11
License-File: LICENSE
Requires-Dist: Jinja2>=3.1.6
Requires-Dist: requests>=2.32.4
Requires-Dist: lxml>=5.4.0
Requires-Dist: xmltodict>=0.14.2
Dynamic: author
Dynamic: author-email
Dynamic: classifier
Dynamic: description
Dynamic: description-content-type
Dynamic: home-page
Dynamic: license
Dynamic: license-file
Dynamic: project-url
Dynamic: requires-dist
Dynamic: requires-python
Dynamic: summary
